texteller/__init__.py
texteller/constants.py
texteller/globals.py
texteller/logger.py
texteller/api/__init__.py
texteller/api/format.py
texteller/api/inference.py
texteller/api/katex.py
texteller/api/load.py
texteller/api/criterias/__init__.py
texteller/api/criterias/ngram.py
texteller/api/detection/__init__.py
texteller/api/detection/detect.py
texteller/api/detection/preprocess.py
texteller/cli/__init__.py
texteller/cli/commands/__init__.py
texteller/cli/commands/inference.py
texteller/cli/commands/launch/__init__.py
texteller/cli/commands/launch/server.py
texteller/cli/commands/web/__init__.py
texteller/cli/commands/web/streamlit_demo.py
texteller/cli/commands/web/style.py
texteller/models/__init__.py
texteller/models/texteller.py
texteller/paddleocr/CTCLabelDecode.py
texteller/paddleocr/DBPostProcess.py
texteller/paddleocr/operators.py
texteller/paddleocr/ppocr_keys_v1.txt
texteller/paddleocr/predict_det.py
texteller/paddleocr/predict_rec.py
texteller/paddleocr/utility.py
texteller/types/__init__.py
texteller/types/bbox.py
texteller/utils/__init__.py
texteller/utils/bbox.py
texteller/utils/device.py
texteller/utils/image.py
texteller/utils/latex.py
texteller/utils/misc.py
texteller/utils/path.py
texteller-1.0.2.dist-info/METADATA
texteller-1.0.2.dist-info/WHEEL
texteller-1.0.2.dist-info/entry_points.txt
texteller-1.0.2.dist-info/licenses/LICENSE
texteller-1.0.2.dist-info/RECORD
