Metadata-Version: 2.4
Name: texteller
Version: 1.0.2
Summary: Texteller is a tool for converting rendered image to original latex code
Author-email: OleehyO <leehy0357@gmail.com>
License: 
License-File: LICENSE
Requires-Python: >=3.10
Requires-Dist: click>=8.1.8
Requires-Dist: colorama>=0.4.6
Requires-Dist: opencv-python-headless>=4.11.0.86
Requires-Dist: optimum[onnxruntime]>=1.24.0
Requires-Dist: pyclipper>=1.3.0.post6
Requires-Dist: python-multipart>=0.0.20
Requires-Dist: ray[serve]>=2.44.1
Requires-Dist: shapely>=2.1.0
Requires-Dist: streamlit-paste-button>=0.1.2
Requires-Dist: streamlit>=1.44.1
Requires-Dist: torch>=2.6.0
Requires-Dist: torchvision>=0.21.0
Requires-Dist: transformers==4.47
Requires-Dist: wget>=3.2
Provides-Extra: docs
Requires-Dist: myst-parser>=4.0.1; extra == 'docs'
Requires-Dist: nbsphinx>=0.9.7; extra == 'docs'
Requires-Dist: sphinx-book-theme>=1.1.4; extra == 'docs'
Requires-Dist: sphinx-copybutton>=0.5.2; extra == 'docs'
Requires-Dist: sphinx-design>=0.6.1; extra == 'docs'
Requires-Dist: sphinx>=8.1.3; extra == 'docs'
Provides-Extra: onnxruntime-gpu
Requires-Dist: onnxruntime-gpu>=1.21.0; extra == 'onnxruntime-gpu'
Provides-Extra: test
Requires-Dist: pytest>=8.3.5; extra == 'test'
Provides-Extra: train
Requires-Dist: accelerate>=1.6.0; extra == 'train'
Requires-Dist: augraphy>=8.2.6; extra == 'train'
Requires-Dist: datasets>=3.5.0; extra == 'train'
Requires-Dist: tensorboardx>=2.6.2.2; extra == 'train'
